bugzilla_docstrings/__init__.py
bugzilla_docstrings/checker.py
bugzilla_docstrings/flake8_plugin.py
bugzilla_docstrings/parser.py
bugzilla_docstrings/utils.py
bugzilla_docstrings-0.0.1.dist-info/METADATA
bugzilla_docstrings-0.0.1.dist-info/WHEEL
bugzilla_docstrings-0.0.1.dist-info/entry_points.txt
bugzilla_docstrings-0.0.1.dist-info/top_level.txt
bugzilla_docstrings-0.0.1.dist-info/RECORD
