Metadata-Version: 2.1
Name: bugzilla-docstrings
Version: 0.0.1
Summary: Reads Bugzilla docstrings and validates them using flake8
Home-page: https://gitlab.com/jdupuy/bugzilla_docstrings
Author: Martin Kourim
Author-email: mkourim@redhat.com
License: MIT
Keywords: bugzilla,testing
Platform: UNKNOWN
Classifier: Development Status :: 3 - Alpha
Classifier: Topic :: Software Development :: Libraries :: Python Modules
Classifier: Topic :: Software Development :: Testing
Classifier: License :: OSI Approved :: MIT License
Classifier: Programming Language :: Python :: 2.7
Classifier: Programming Language :: Python :: 3.4
Classifier: Programming Language :: Python :: 3.5
Classifier: Programming Language :: Python :: 3.6
Classifier: Programming Language :: Python :: 3.7
Classifier: Intended Audience :: Developers
Requires-Dist: pyyaml
